folder_structure_generator_7edge/__init__.py
folder_structure_generator_7edge/generator.py
folder_structure_generator_7edge/hooks-template.py
dynamic_folder_creation_test-1.0.0.dist-info/METADATA
dynamic_folder_creation_test-1.0.0.dist-info/WHEEL
dynamic_folder_creation_test-1.0.0.dist-info/entry_points.txt
dynamic_folder_creation_test-1.0.0.dist-info/top_level.txt
dynamic_folder_creation_test-1.0.0.dist-info/RECORD
